{"neurons":[{"trace":{"elegibility":{},"extended":{}},"state":0,"old":0,"activation":1,"bias":0,"layer":"input","squash":"LOGISTIC"},{"trace":{"elegibility":{},"extended":{}},"state":0,"old":0,"activation":1,"bias":0,"layer":"input","squash":"LOGISTIC"},{"trace":{"elegibility":{},"extended":{}},"state":-4.185240866132128,"old":-9.823068261814553,"activation":0.014990407751553624,"bias":-2.5082475355288962,"layer":"0","squash":"LOGISTIC"},{"trace":{"elegibility":{},"extended":{}},"state":6.215516223677747,"old":2.775826340101828,"activation":0.9980058002053362,"bias":-0.01083048612823183,"layer":"0","squash":"LOGISTIC"},{"trace":{"elegibility":{},"extended":{}},"state":3.47102191933373,"old":1.7908179317666841,"activation":0.9698519129485984,"bias":0.9650641573314133,"layer":"0","squash":"LOGISTIC"},{"trace":{"elegibility":{},"extended":{}},"state":4.485077888927282,"old":-3.5295392813510147,"activation":0.9888497214335383,"bias":3.3812045610220793,"layer":"0","squash":"LOGISTIC"},{"trace":{"elegibility":{},"extended":{}},"state":-5.7545438428198015,"old":6.187293236133364,"activation":0.003158344801146519,"bias":1.130080925556604,"layer":"output","squash":"LOGISTIC"}],"connections":[{"from":"0","to":"2","weight":5.637827395682425,"gater":null},{"from":"0","to":"3","weight":3.4396898835759186,"gater":null},{"from":"0","to":"4","weight":1.6802039875670458,"gater":null},{"from":"0","to":"5","weight":8.014617170278298,"gater":null},{"from":"1","to":"2","weight":-7.3148207262856575,"gater":null},{"from":"1","to":"3","weight":2.7866568262300597,"gater":null},{"from":"1","to":"4","weight":0.8257537744352709,"gater":null},{"from":"1","to":"5","weight":-6.910743842373094,"gater":null},{"from":"2","to":"6","weight":12.984714966830436,"gater":null},{"from":"3","to":"6","weight":3.9251847257126364,"gater":null},{"from":"4","to":"6","weight":2.0242245257978175,"gater":null},{"from":"5","to":"6","weight":-13.105961210364788,"gater":null}]}